{"cameraMode":{"drawMode":0,"name":"Shaded","section":"Shading Mode"},"sceneLighting":true,"audioPlay":false,"sceneViewState":{"showFog":true,"showMaterialUpdate":false,"showSkybox":true,"showFlares":true,"showImageEffects":true,"showParticleSystems":true},"in2DMode":false,"pivot":{"x":-132.55361938476563,"y":271.8017578125,"z":-228.2640838623047},"rotation":{"x":-0.25054967403411868,"y":0.47540080547332766,"z":-0.1433214694261551,"w":-0.8310794234275818},"size":173.30198669433595,"orthographic":false}